{
    "fortress": {
        "base_hp": 18000,
        "base_dps_ground": 80,
        "base_dps_air": 0,
        "range": 20,
        "speed": 4,
        "squad_size": 1,
        "can_hit_ground": true,
        "can_hit_air": false,
        "prefers_chaff": false,
        "prefers_heavy": false,
        "splash": false,
        "tags": ["heavy_frontline", "tank", "melee"]
    },
    "marksmen": {
        "base_hp": 160,
        "base_dps_ground": 90,
        "base_dps_air": 90,
        "range": 120,
        "speed": 6,
        "squad_size": 6,
        "can_hit_ground": true,
        "can_hit_air": true,
        "prefers_chaff": false,
        "prefers_heavy": true,
        "splash": false,
        "tags": ["anti_air", "single_target", "artillery", "ranged"]
    },
    "vulcan": {
        "base_hp": 5500,
        "base_dps_ground": 200,
        "base_dps_air": 0,
        "range": 55,
        "speed": 0,
        "squad_size": 1,
        "can_hit_ground": true,
        "can_hit_air": false,
        "prefers_chaff": true,
        "prefers_heavy": false,
        "splash": true,
        "tags": ["anti_chaff", "splash", "stationary"]
    },
    "melting point": {
        "base_hp": 3800,
        "base_dps_ground": 150,
        "base_dps_air": 0,
        "range": 100,
        "speed": 0,
        "squad_size": 1,
        "can_hit_ground": true,
        "can_hit_air": false,
        "prefers_chaff": false,
        "prefers_heavy": true,
        "splash": false,
        "tags": ["single_target", "artillery", "ranged"]
    },
    "rhino": {
        "base_hp": 8000,
        "base_dps_ground": 45,
        "base_dps_air": 0,
        "range": 15,
        "speed": 8,
        "squad_size": 1,
        "can_hit_ground": true,
        "can_hit_air": false,
        "prefers_chaff": false,
        "prefers_heavy": false,
        "splash": false,
        "tags": ["heavy_frontline", "tank", "melee"]
    },
    "wasp": {
        "base_hp": 150,
        "base_dps_ground": 35,
        "base_dps_air": 0,
        "range": 25,
        "speed": 14,
        "squad_size": 8,
        "can_hit_ground": true,
        "can_hit_air": false,
        "prefers_chaff": false,
        "prefers_heavy": false,
        "splash": false,
        "tags": ["air", "flank_pressure"]
    },
    "mustang": {
        "base_hp": 200,
        "base_dps_ground": 55,
        "base_dps_air": 75,
        "range": 80,
        "speed": 6,
        "squad_size": 4,
        "can_hit_ground": true,
        "can_hit_air": true,
        "prefers_chaff": true,
        "prefers_heavy": false,
        "splash": true,
        "tags": ["anti_air", "anti_chaff", "ranged"]
    },
    "steel ball": {
        "base_hp": 5000,
        "base_dps_ground": 60,
        "base_dps_air": 0,
        "range": 15,
        "speed": 7,
        "squad_size": 2,
        "can_hit_ground": true,
        "can_hit_air": false,
        "prefers_chaff": false,
        "prefers_heavy": false,
        "splash": true,
        "tags": ["heavy_frontline", "tank", "melee"]
    },
    "fang": {
        "base_hp": 180,
        "base_dps_ground": 20,
        "base_dps_air": 0,
        "range": 10,
        "speed": 14,
        "squad_size": 12,
        "can_hit_ground": true,
        "can_hit_air": false,
        "prefers_chaff": false,
        "prefers_heavy": false,
        "splash": false,
        "tags": ["chaff", "melee", "flank_pressure"]
    },
    "crawler": {
        "base_hp": 290,
        "base_dps_ground": 23,
        "base_dps_air": 0,
        "range": 10,
        "speed": 12,
        "squad_size": 24,
        "can_hit_ground": true,
        "can_hit_air": false,
        "prefers_chaff": false,
        "prefers_heavy": false,
        "splash": false,
        "tags": ["chaff", "melee"]
    },
    "overlord": {
        "base_hp": 12000,
        "base_dps_ground": 120,
        "base_dps_air": 0,
        "range": 60,
        "speed": 5,
        "squad_size": 1,
        "can_hit_ground": true,
        "can_hit_air": false,
        "prefers_chaff": false,
        "prefers_heavy": false,
        "splash": true,
        "tags": ["air", "backline_carry", "scaling"]
    },
    "stormcaller": {
        "base_hp": 350,
        "base_dps_ground": 70,
        "base_dps_air": 50,
        "range": 90,
        "speed": 5,
        "squad_size": 4,
        "can_hit_ground": true,
        "can_hit_air": true,
        "prefers_chaff": true,
        "prefers_heavy": false,
        "splash": true,
        "tags": ["artillery", "anti_chaff", "anti_air", "ranged"]
    },
    "sledgehammer": {
        "base_hp": 450,
        "base_dps_ground": 100,
        "base_dps_air": 0,
        "range": 110,
        "speed": 5,
        "squad_size": 4,
        "can_hit_ground": true,
        "can_hit_air": false,
        "prefers_chaff": false,
        "prefers_heavy": false,
        "splash": true,
        "tags": ["artillery", "ranged"]
    },
    "hacker": {
        "base_hp": 3000,
        "base_dps_ground": 30,
        "base_dps_air": 0,
        "range": 60,
        "speed": 5,
        "squad_size": 1,
        "can_hit_ground": true,
        "can_hit_air": false,
        "prefers_chaff": false,
        "prefers_heavy": false,
        "splash": false,
        "tags": ["support", "debuff"]
    },
    "arclight": {
        "base_hp": 220,
        "base_dps_ground": 45,
        "base_dps_air": 60,
        "range": 70,
        "speed": 6,
        "squad_size": 6,
        "can_hit_ground": true,
        "can_hit_air": true,
        "prefers_chaff": true,
        "prefers_heavy": false,
        "splash": false,
        "tags": ["anti_air", "anti_chaff", "ranged"]
    },
    "phoenix": {
        "base_hp": 4500,
        "base_dps_ground": 110,
        "base_dps_air": 0,
        "range": 40,
        "speed": 10,
        "squad_size": 1,
        "can_hit_ground": true,
        "can_hit_air": false,
        "prefers_chaff": false,
        "prefers_heavy": true,
        "splash": false,
        "tags": ["air", "single_target", "flank_pressure"]
    },
    "warfactory": {
        "base_hp": 25000,
        "base_dps_ground": 40,
        "base_dps_air": 0,
        "range": 30,
        "speed": 0,
        "squad_size": 1,
        "can_hit_ground": true,
        "can_hit_air": false,
        "prefers_chaff": false,
        "prefers_heavy": false,
        "splash": false,
        "tags": ["backline_carry", "scaling", "stationary"]
    },
    "wraith": {
        "base_hp": 6000,
        "base_dps_ground": 85,
        "base_dps_air": 0,
        "range": 50,
        "speed": 8,
        "squad_size": 1,
        "can_hit_ground": true,
        "can_hit_air": false,
        "prefers_chaff": false,
        "prefers_heavy": false,
        "splash": true,
        "tags": ["air", "scaling", "backline_carry"]
    },
    "scorpion": {
        "base_hp": 2800,
        "base_dps_ground": 130,
        "base_dps_air": 0,
        "range": 100,
        "speed": 5,
        "squad_size": 1,
        "can_hit_ground": true,
        "can_hit_air": false,
        "prefers_chaff": false,
        "prefers_heavy": true,
        "splash": false,
        "tags": ["single_target", "artillery", "ranged", "scaling"]
    },
    "fire badger": {
        "base_hp": 400,
        "base_dps_ground": 65,
        "base_dps_air": 0,
        "range": 40,
        "speed": 10,
        "squad_size": 4,
        "can_hit_ground": true,
        "can_hit_air": false,
        "prefers_chaff": true,
        "prefers_heavy": false,
        "splash": true,
        "tags": ["anti_chaff", "splash"]
    },
    "sabertooth": {
        "base_hp": 7000,
        "base_dps_ground": 55,
        "base_dps_air": 0,
        "range": 15,
        "speed": 7,
        "squad_size": 1,
        "can_hit_ground": true,
        "can_hit_air": false,
        "prefers_chaff": false,
        "prefers_heavy": false,
        "splash": false,
        "tags": ["heavy_frontline", "tank", "melee"]
    },
    "typhoon": {
        "base_hp": 5500,
        "base_dps_ground": 95,
        "base_dps_air": 0,
        "range": 45,
        "speed": 9,
        "squad_size": 1,
        "can_hit_ground": true,
        "can_hit_air": false,
        "prefers_chaff": false,
        "prefers_heavy": false,
        "splash": true,
        "tags": ["air", "flank_pressure", "splash"]
    },
    "sandworm": {
        "base_hp": 22000,
        "base_dps_ground": 70,
        "base_dps_air": 0,
        "range": 15,
        "speed": 5,
        "squad_size": 1,
        "can_hit_ground": true,
        "can_hit_air": false,
        "prefers_chaff": false,
        "prefers_heavy": false,
        "splash": true,
        "tags": ["heavy_frontline", "tank", "melee"]
    },
    "tarantula": {
        "base_hp": 6500,
        "base_dps_ground": 50,
        "base_dps_air": 0,
        "range": 20,
        "speed": 6,
        "squad_size": 1,
        "can_hit_ground": true,
        "can_hit_air": false,
        "prefers_chaff": false,
        "prefers_heavy": false,
        "splash": false,
        "tags": ["heavy_frontline", "tank", "single_target"]
    },
    "phantom ray": {
        "base_hp": 200,
        "base_dps_ground": 40,
        "base_dps_air": 0,
        "range": 30,
        "speed": 12,
        "squad_size": 6,
        "can_hit_ground": true,
        "can_hit_air": false,
        "prefers_chaff": false,
        "prefers_heavy": false,
        "splash": false,
        "tags": ["air", "flank_pressure"]
    },
    "farseer": {
        "base_hp": 3200,
        "base_dps_ground": 85,
        "base_dps_air": 0,
        "range": 130,
        "speed": 0,
        "squad_size": 1,
        "can_hit_ground": true,
        "can_hit_air": false,
        "prefers_chaff": false,
        "prefers_heavy": false,
        "splash": true,
        "tags": ["artillery", "ranged", "scaling"]
    },
    "raiden": {
        "base_hp": 5000,
        "base_dps_ground": 140,
        "base_dps_air": 0,
        "range": 95,
        "speed": 0,
        "squad_size": 1,
        "can_hit_ground": true,
        "can_hit_air": false,
        "prefers_chaff": false,
        "prefers_heavy": true,
        "splash": false,
        "tags": ["single_target", "ranged", "scaling"]
    },
    "hound": {
        "base_hp": 250,
        "base_dps_ground": 18,
        "base_dps_air": 0,
        "range": 10,
        "speed": 16,
        "squad_size": 8,
        "can_hit_ground": true,
        "can_hit_air": false,
        "prefers_chaff": false,
        "prefers_heavy": false,
        "splash": false,
        "tags": ["chaff", "melee", "flank_pressure"]
    },
    "abyss": {
        "base_hp": 30000,
        "base_dps_ground": 60,
        "base_dps_air": 0,
        "range": 25,
        "speed": 3,
        "squad_size": 1,
        "can_hit_ground": true,
        "can_hit_air": false,
        "prefers_chaff": false,
        "prefers_heavy": false,
        "splash": true,
        "tags": ["backline_carry", "scaling", "tank"]
    }
}
